enrichmentanalysis/__init__.py
enrichmentanalysis/cli.py
enrichmentanalysis/enrich_rec.py
enrichmentanalysis/enrich_results.py
enrichmentanalysis/enrich_run.py
enrichmentanalysis/file_utils.py
enrichmentanalysis/multiple_testing.py
enrichmentanalysis/pvalcalc.py
enrichmentanalysis/report_results.py
enrichmentanalysis/wr_tbl.py
enrichmentanalysis/wr_tbl_class.py
enrichmentanalysis_dvklopfenstein-0.0.10.data/scripts/run_enrichment.py
enrichmentanalysis_dvklopfenstein-0.0.10.dist-info/LICENSE
enrichmentanalysis_dvklopfenstein-0.0.10.dist-info/METADATA
enrichmentanalysis_dvklopfenstein-0.0.10.dist-info/WHEEL
enrichmentanalysis_dvklopfenstein-0.0.10.dist-info/top_level.txt
enrichmentanalysis_dvklopfenstein-0.0.10.dist-info/RECORD
