Metadata-Version: 2.1
Name: enrichmentanalysis-dvklopfenstein
Version: 0.0.10
Summary: Perform enrichment analysis on any IDs and associations
Home-page: http://github.com/dvklopfenstein/enrichmentanalysis
Author: DV Klopfenstein
Author-email: dvklopfenstein@gmail.com
License: UNKNOWN
Platform: UNKNOWN
Classifier: Development Status :: 4 - Beta
Classifier: Intended Audience :: Science/Research
Classifier: License :: OSI Approved :: BSD License
Classifier: Programming Language :: Python :: 3
Classifier: Topic :: Scientific/Engineering :: Bio-Informatics
Classifier: Operating System :: OS Independent
Requires-Dist: docopt
Requires-Dist: xlsxwriter
